fem/__init__.py
fem/fem.py
fem/simulation.py
fem-0.0.1.dist-info/METADATA
fem-0.0.1.dist-info/RECORD
fem-0.0.1.dist-info/WHEEL
fem-0.0.1.dist-info/top_level.txt
